houston/__init__.py
houston/__main__.py
houston/client.py
houston/commands.py
houston/exceptions.py
houston/interface.py
houston/plan.py
houston/service.py
houston/gcp/__init__.py
houston/gcp/client.py
houston/gcp/cloud_function.py
houston/gcp/cloud_storage.py
houston/gcp/secret_manager.py
houston/plugin/__init__.py
houston/plugin/azure.py
houston/plugin/gcp.py
houston_client-1.3.1.dist-info/LICENSE
houston_client-1.3.1.dist-info/METADATA
houston_client-1.3.1.dist-info/WHEEL
houston_client-1.3.1.dist-info/top_level.txt
houston_client-1.3.1.dist-info/RECORD
