Metadata-Version: 2.1
Name: houston-client
Version: 1.3.1
Summary: Houston Python Client
Author-email: James Watkinson <info@datasparq.ai>, Matt Simmons <info@datasparq.ai>
License: MIT License
Project-URL: Homepage, https://github.com/datasparq-ai/houston
Project-URL: Documentation, https://github.com/datasparq-ai/houston/blob/main/docs
Project-URL: Source, https://github.com/datasparq-intelligent-products/houston-python
Keywords: houston
Classifier: Programming Language :: Python :: 3
Classifier: Programming Language :: Python :: 3.9
Classifier: Programming Language :: Python :: 3.10
Classifier: Operating System :: OS Independent
Requires-Python: >=3.7
License-File: LICENSE
Requires-Dist: requests (<3.0.0dev,>=2.18.0)
Requires-Dist: requests[security] (<3.0.0dev,>=2.18.0)
Requires-Dist: PyYAML
Requires-Dist: retry (<1,>=0.9.2)
Provides-Extra: azure
Requires-Dist: azure-eventgrid (>=1.2.0) ; extra == 'azure'
Requires-Dist: azure-mgmt-eventgrid (>=2.2.0) ; extra == 'azure'
Provides-Extra: gcp
Requires-Dist: google-cloud-secret-manager (>=2.5) ; extra == 'gcp'
Requires-Dist: google-cloud-pubsub (>=1.2) ; extra == 'gcp'
Requires-Dist: google-cloud-storage (>=1.35) ; extra == 'gcp'
Requires-Dist: google-cloud-logging (>=2) ; extra == 'gcp'
